mlmetrics/__init__.py
mlmetrics/client.py
mlmetrics_io-0.1.0.dist-info/LICENSE
mlmetrics_io-0.1.0.dist-info/METADATA
mlmetrics_io-0.1.0.dist-info/WHEEL
mlmetrics_io-0.1.0.dist-info/top_level.txt
mlmetrics_io-0.1.0.dist-info/RECORD
